{
  "generator-jhipster": {
    "applicationIndex": 2,
    "applicationType": "microservice",
    "authenticationType": "oauth2",
    "baseName": "eRestaurantRestaurant",
    "blueprints": [],
    "buildTool": "maven",
    "cacheProvider": "no",
    "clientPackageManager": "npm",
    "creationTimestamp": 1655853824063,
    "databaseType": "sql",
    "devDatabaseType": "h2Disk",
    "dtoSuffix": "DTO",
    "enableGradleEnterprise": false,
    "enableHibernateCache": false,
    "enableSwaggerCodegen": false,
    "enableTranslation": true,
    "entities": [
      "Restaurant",
      "Discount",
      "RestaurantDiscount",
      "Notification",
      "NotificationType",
      "Employee",
      "Ad",
      "RestaurantAd",
      "AppUser",
      "Categories",
      "Products"
    ],
    "entitySuffix": "",
    "gatewayServerPort": "8080",
    "gradleEnterpriseHost": "",
    "jhiPrefix": "jhi",
    "jhipsterVersion": "7.8.1",
    "jwtSecretKey": "NTM0Njc1MDAzNWE2MjEyZGU0OTgxNjM4ZGQ2Y2E5ZTRlMDc5ZjYyN2ZjNmQ3YjhkOTcwZjVjOWU4OGY2NmY5YTk4OTIxOTcwOGFhMjQ1OTAwZDRlMGY4OTZiMjBmNGQxMDFiNzRlMGMwZjJkYzRiMDY3MzhhY2ZjZGZlY2Q3MDc=",
    "languages": ["en", "pl", "fr", "es", "de", "it", "ro"],
    "lastLiquibaseTimestamp": 1655853838000,
    "messageBroker": "kafka",
    "monorepository": true,
    "nativeLanguage": "en",
    "otherModules": [],
    "packageFolder": "com/erestaurant/restautant",
    "packageName": "com.erestaurant.restautant",
    "pages": [],
    "prodDatabaseType": "postgresql",
    "reactive": true,
    "searchEngine": "elasticsearch",
    "serverPort": "8083",
    "serviceDiscoveryType": "eureka",
    "skipCheckLengthOfIdentifier": false,
    "skipClient": true,
    "skipCommitHook": true,
    "skipFakeData": false,
    "skipUserManagement": true,
    "testFrameworks": [],
    "websocket": false,
    "withAdminUi": false
  }
}
